{
  "juz_1": {
    "quarter_1": {
      "start": [
        1,
        1
      ],
      "end": [
        2,
        46
      ]
    },
    "quarter_2": {
      "start": [
        2,
        47
      ],
      "end": [
        2,
        82
      ]
    },
    "quarter_3": {
      "start": [
        2,
        83
      ],
      "end": [
        2,
        112
      ]
    },
    "quarter_4": {
      "start": [
        2,
        113
      ],
      "end": [
        2,
        141
      ]
    }
  },
  "juz_2": {
    "quarter_1": {
      "start": [
        2,
        142
      ],
      "end": [
        2,
        176
      ]
    },
    "quarter_2": {
      "start": [
        2,
        177
      ],
      "end": [
        2,
        210
      ]
    },
    "quarter_3": {
      "start": [
        2,
        211
      ],
      "end": [
        2,
        231
      ]
    },
    "quarter_4": {
      "start": [
        2,
        232
      ],
      "end": [
        2,
        252
      ]
    }
  },
  "juz_3": {
    "quarter_1": {
      "start": [
        2,
        253
      ],
      "end": [
        2,
        273
      ]
    },
    "quarter_2": {
      "start": [
        2,
        274
      ],
      "end": [
        3,
        14
      ]
    },
    "quarter_3": {
      "start": [
        3,
        15
      ],
      "end": [
        3,
        51
      ]
    },
    "quarter_4": {
      "start": [
        3,
        52
      ],
      "end": [
        3,
        91
      ]
    }
  }
}
